odoo/addons/stock_location_address_purchase/README.rst
odoo/addons/stock_location_address_purchase/__init__.py
odoo/addons/stock_location_address_purchase/__manifest__.py
odoo/addons/stock_location_address_purchase/models/__init__.py
odoo/addons/stock_location_address_purchase/models/purchase.py
odoo/addons/stock_location_address_purchase/static/description/icon.png
odoo/addons/stock_location_address_purchase/tests/__init__.py
odoo/addons/stock_location_address_purchase/tests/test_purchase_address.py
odoo11_addon_stock_location_address_purchase-11.0.1.0.0.99.dev1.dist-info/DESCRIPTION.rst
odoo11_addon_stock_location_address_purchase-11.0.1.0.0.99.dev1.dist-info/METADATA
odoo11_addon_stock_location_address_purchase-11.0.1.0.0.99.dev1.dist-info/RECORD
odoo11_addon_stock_location_address_purchase-11.0.1.0.0.99.dev1.dist-info/WHEEL
odoo11_addon_stock_location_address_purchase-11.0.1.0.0.99.dev1.dist-info/metadata.json
odoo11_addon_stock_location_address_purchase-11.0.1.0.0.99.dev1.dist-info/top_level.txt
